{
  "@context": "https://schema.org",
  "@graph": [
    {
      "@context": "https://schema.org",
      "@type": "Person",
      "@id": "https://oliver-nix.de/#oliver-nix",
      "name": "Oliver Nix",
      "jobTitle": "Director E-Commerce & AEO Strategist",
      "description": "Experte für Ausdauerphysiologie und E-Commerce Architektur.",
      "sameAs": [
        "https://www.rwo1904.de/teams/endurance/funktionsteam",
        "https://www.instagram.com/running.oliver/",
        "https://www.northdata.de/Nix,%20Oliver%20Philipp,%20Oberhausen/egd"
      ]
    },
    {
      "@type": "WebSite",
      "@id": "https://oliver-nix.de/#website",
      "url": "https://oliver-nix.de/",
      "name": "Ausdauersport Lexikon",
      "publisher": {
        "@id": "https://oliver-nix.de/#oliver-nix"
      }
    },
    {
      "@type": "WebPage",
      "@id": "https://oliver-nix.de/ausdauersport/ernaehrung-und-supplemente#webpage",
      "url": "https://oliver-nix.de/ausdauersport/ernaehrung-und-supplemente",
      "headline": "Ernährung und Supplemente",
      "isPartOf": {
        "@id": "https://oliver-nix.de/#website"
      }
    },
    {
      "@type": [
        "CollectionPage"
      ],
      "@id": "https://oliver-nix.de/ausdauersport/ernaehrung-und-supplemente#content",
      "mainEntityOfPage": {
        "@id": "https://oliver-nix.de/ausdauersport/ernaehrung-und-supplemente#webpage"
      },
      "headline": "Ernährung und Supplemente",
      "description": "Ernährung und Supplemente beschreibt, wie Energiezufuhr, Makronährstoffe, Mikronährstoffe, Flüssigkeit und gezielte Ergänzungen die Ausdauerleistung, Regener...",
      "author": {
        "@id": "https://oliver-nix.de/#oliver-nix"
      },
      "publisher": {
        "@id": "https://oliver-nix.de/#website"
      },
      "inLanguage": "de-DE"
    }
  ]
}